sqlcipher3/__init__.py
sqlcipher3/__init__.pyi
sqlcipher3/_sqlite3.cpython-314t-x86_64-linux-gnu.so
sqlcipher3/dbapi2.py
sqlcipher3/dbapi2.pyi
sqlcipher3/py.typed
sqlcipher3_wheels-0.5.7.dist-info/METADATA
sqlcipher3_wheels-0.5.7.dist-info/WHEEL
sqlcipher3_wheels-0.5.7.dist-info/top_level.txt
sqlcipher3_wheels-0.5.7.dist-info/RECORD
sqlcipher3_wheels-0.5.7.dist-info/licenses/LICENSE
