Metadata-Version: 2.4
Name: sqlcipher3-wheels
Version: 0.5.7
Summary: DB-API 2.0 interface for SQLCipher 3.x
Author-email: Charles Leifer <coleifer@gmail.com>, laggykiller <chaudominic2@gmail.com>
License: zlib/libpng
Project-URL: homepage, https://github.com/laggykiller/sqlcipher3
Classifier: Development Status :: 4 - Beta
Classifier: Intended Audience :: Developers
Classifier: Operating System :: MacOS :: MacOS X
Classifier: Operating System :: Microsoft :: Windows
Classifier: Operating System :: POSIX
Classifier: Programming Language :: C
Classifier: Programming Language :: Python
Classifier: Topic :: Database :: Database Engines/Servers
Classifier: Topic :: Software Development :: Libraries :: Python Modules
License-File: LICENSE
Dynamic: license-file
